{
    "31":  {
               "folder":  "mountain-adventures-crete",
               "images":  [
                              "image-1.jpg",
                              "image-10.jpg",
                              "image-11.jpg",
                              "image-12.jpg",
                              "image-13.jpg",
                              "image-14.jpg",
                              "image-2.jpg",
                              "image-3.jpg",
                              "image-4.jpg",
                              "image-5.jpg",
                              "image-6.jpg",
                              "image-7.jpg",
                              "image-8.jpg",
                              "image-9.jpg"
                          ]
           },
    "12":  {
               "folder":  "sea-aura-apartment",
               "images":  [
                              "image-1.jpg",
                              "image-10.jpg",
                              "image-11.jpg",
                              "image-2.jpg",
                              "image-3.jpg",
                              "image-4.jpg",
                              "image-5.jpg",
                              "image-6.jpg",
                              "image-7.jpg",
                              "image-8.jpg",
                              "image-9.jpg"
                          ]
           },
    "2":  {
              "folder":  "sougia-taxi",
              "images":  [
                             "image-1.jpg",
                             "image-2.jpg",
                             "image-3.jpg",
                             "image-4.jpg",
                             "image-5.jpg",
                             "image-6.jpg"
                         ]
          },
    "29":  {
               "folder":  "sunset-taverna",
               "images":  [
                              "image-1.jpg",
                              "image-10.jpg",
                              "image-11.jpg",
                              "image-12.jpg",
                              "image-13.jpg",
                              "image-14.jpg",
                              "image-15.jpg",
                              "image-16.jpg",
                              "image-17.jpg",
                              "image-2.jpg",
                              "image-3.jpg",
                              "image-4.jpg",
                              "image-5.jpg",
                              "image-6.jpg",
                              "image-7.jpg",
                              "image-8.jpg",
                              "image-9.jpg"
                          ]
           },
    "23":  {
               "folder":  "greek-cook-out",
               "images":  [
                              "image-1.jpg",
                              "image-10.jpg",
                              "image-11.jpg",
                              "image-12.jpg",
                              "image-13.jpg",
                              "image-14.jpg",
                              "image-15.jpg",
                              "image-16.jpg",
                              "image-17.jpg",
                              "image-2.jpg",
                              "image-3.jpg",
                              "image-4.jpg",
                              "image-5.jpg",
                              "image-6.jpg",
                              "image-7.jpg",
                              "image-8.jpg",
                              "image-9.jpg"
                          ]
           },
    "11":  {
               "folder":  "lovely-seaside-studio",
               "images":  [
                              "image-1.jpg",
                              "image-2.jpg",
                              "image-3.jpg",
                              "image-4.jpg",
                              "image-5.jpg",
                              "image-6.jpg",
                              "image-7.jpg",
                              "image-8.jpg",
                              "image-9.jpg"
                          ]
           },
    "1":  {
              "folder":  "vittorakis-travel",
              "images":  [
                             "image-1.jpg",
                             "image-10.jpg",
                             "image-11.jpg",
                             "image-12.jpg",
                             "image-13.jpg",
                             "image-14.jpg",
                             "image-2.jpg",
                             "image-3.jpg",
                             "image-4.jpg",
                             "image-5.jpg",
                             "image-6.jpg",
                             "image-7.jpg",
                             "image-8.jpg",
                             "image-9.jpg"
                         ]
          },
    "28":  {
               "folder":  "heraklion-premium-cars",
               "images":  [
                              "image-1.jpg",
                              "image-2.jpg",
                              "image-3.jpg",
                              "image-4.jpg",
                              "image-5.jpg"
                          ]
           },
    "24":  {
               "folder":  "chania-car-rental",
               "images":  [
                              "image-1.jpg",
                              "image-2.jpg",
                              "image-3.jpg",
                              "image-4.jpg",
                              "image-5.jpg"
                          ]
           },
    "16":  {
               "folder":  "alina-rent-car",
               "images":  [
                              "image-1.jpg",
                              "image-2.jpg",
                              "image-3.jpg",
                              "image-4.jpg",
                              "image-5.jpg"
                          ]
           },
    "25":  {
               "folder":  "taverna-akrogiali",
               "images":  [
                              "image-1.jpg",
                              "image-10.jpg",
                              "image-11.jpg",
                              "image-12.jpg",
                              "image-13.jpg",
                              "image-14.jpg",
                              "image-15.jpg",
                              "image-16.jpg",
                              "image-17.jpg",
                              "image-2.jpg",
                              "image-3.jpg",
                              "image-4.jpg",
                              "image-5.jpg",
                              "image-6.jpg",
                              "image-7.jpg",
                              "image-8.jpg",
                              "image-9.jpg"
                          ]
           },
    "27":  {
               "folder":  "blue-sea-apartments",
               "images":  [
                              "image-1.jpg",
                              "image-2.jpg",
                              "image-3.jpg",
                              "image-4.jpg",
                              "image-5.jpg",
                              "image-6.jpg",
                              "image-7.jpg",
                              "image-8.jpg",
                              "image-9.jpg"
                          ]
           },
    "30":  {
               "folder":  "chania-boat-tours",
               "images":  [
                              "image-1.jpg",
                              "image-10.jpg",
                              "image-2.jpg",
                              "image-3.jpg",
                              "image-4.jpg",
                              "image-5.jpg",
                              "image-6.jpg",
                              "image-7.jpg",
                              "image-8.jpg",
                              "image-9.jpg"
                          ]
           },
    "4":  {
              "folder":  "malia-cruises",
              "images":  [
                             "image-1.jpg",
                             "image-10.jpg",
                             "image-2.jpg",
                             "image-3.jpg",
                             "image-4.jpg",
                             "image-5.jpg",
                             "image-6.jpg",
                             "image-7.jpg",
                             "image-8.jpg",
                             "image-9.jpg"
                         ]
          },
    "26":  {
               "folder":  "heraklion-express-taxi",
               "images":  [
                              "image-1.jpg",
                              "image-10.jpg",
                              "image-11.jpg",
                              "image-12.jpg",
                              "image-13.jpg",
                              "image-14.jpg",
                              "image-2.jpg",
                              "image-3.jpg",
                              "image-4.jpg",
                              "image-5.jpg",
                              "image-6.jpg",
                              "image-7.jpg",
                              "image-8.jpg",
                              "image-9.jpg"
                          ]
           }
}
